Metadata-Version: 2.1
Name: sphinxcontrib.embedding
Version: 0.6.0
Summary: iframe embedding
Home-page: https://qiita.com/tags/sphinxcontrib.embedding
Author: @koKekkoh
Maintainer: KaKkou
License: BSD 2-Clause License
Keywords: sphinx,sphinxcontrib,embedding
Platform: any
Classifier: Development Status :: 3 - Alpha
Classifier: Framework :: Sphinx :: Extension
Classifier: Intended Audience :: Developers
Classifier: Intended Audience :: Education
Classifier: License :: OSI Approved :: BSD License
Classifier: Operating System :: OS Independent
Classifier: Programming Language :: Python :: 3
Classifier: Topic :: Documentation :: Sphinx
Classifier: Topic :: Utilities
License-File: LICENSE
